emu/__init__.py
emu/__main__.py
emu/abstract_syntax_tree.py
emu/code.py
emu/compiler.py
emu/deobfuscation.py
emu/error.py
emu/function.py
emu/interpreter.py
emu/lib/VBA/ColorConstants.py
emu/lib/VBA/Constants.py
emu/lib/VBA/Interaction.py
emu/lib/VBA/Strings.py
emu/lib/WSH/FileHandler.py
emu/lib/WSH/Filesystem.py
emu/lib/WSH/WScript.py
emu/lib/WSH/WshShell.py
emu/lib/__init__.py
emu/operator.py
emu/partial_block.py
emu/preprocessor.py
emu/reference.py
emu/report.py
emu/resources/__init__.py
emu/resources/english_n1.spemu-mancl
emu/serialize.py
emu/side_effect.py
emu/symbol.py
emu/syntax.py
emu/type.py
emu/value.py
emu/vba_class.py
emu/visitor.py
spurious_emu-0.4.1.dist-info/entry_points.txt
spurious_emu-0.4.1.dist-info/LICENSE
spurious_emu-0.4.1.dist-info/WHEEL
spurious_emu-0.4.1.dist-info/METADATA
spurious_emu-0.4.1.dist-info/RECORD
