Metadata-Version: 2.1
Name: spurious-emu
Version: 0.4.1
Summary: VBA static and dynamic analysis tool for malware analysts
Home-page: https://github.com/ldbo/SpuriousEmu
License: AGPL-3.0-or-later
Author: Louis Dubois
Author-email: ldbo@protonmail.com
Requires-Python: >=3.8,<4.0
Classifier: Development Status :: 3 - Alpha
Classifier: Environment :: Console
Classifier: Intended Audience :: Information Technology
Classifier: Intended Audience :: Science/Research
Classifier: License :: OSI Approved :: GNU Affero General Public License v3 or later (AGPLv3+)
Classifier: Natural Language :: English
Classifier: Operating System :: OS Independent
Classifier: Programming Language :: Python :: 3
Classifier: Programming Language :: Python :: 3.8
Classifier: Programming Language :: Visual Basic
Classifier: Topic :: Security
Classifier: Topic :: Software Development :: Interpreters
Requires-Dist: oletools (>=0.55.1,<0.56.0)
Requires-Dist: prettytable (>=0.7.2,<0.8.0)
Requires-Dist: pyparsing (>=2.4.7,<3.0.0)
Requires-Dist: python-magic (>=0.4.18,<0.5.0)
